hta/__init__.py
hta/stats.py
hta/utils.py
hta-0.1.0.dist-info/LICENSE
hta-0.1.0.dist-info/METADATA
hta-0.1.0.dist-info/WHEEL
hta-0.1.0.dist-info/top_level.txt
hta-0.1.0.dist-info/RECORD
