Metadata-Version: 2.1
Name: hta
Version: 0.1.0
Summary: Statistically assess the level of both spatial and global heterogeneity within a spatial sample.
Home-page: https://github.com/alonalj/hta
Author: Alona Levy-Jurgenson
Author-email: levyalona@gmail.com
Project-URL: Bug Tracker, https://github.com/alonalj/hta/issues
Classifier: Programming Language :: Python :: 3
Classifier: License :: OSI Approved :: MIT License
Classifier: Operating System :: OS Independent
Requires-Python: >=3.8
License-File: LICENSE
Requires-Dist: numpy
Requires-Dist: scipy
Requires-Dist: pandas
Requires-Dist: matplotlib
